LICENSE
MANIFEST.in
README.rst
REQUIREMENTS
setup.py
brillixy/__init__.py
brillixy/defaults.py
brillixy/models.py
brillixy/panels.py
brillixy/site.py
brillixy/tests.py
brillixy/views.py
brillixy.egg-info/PKG-INFO
brillixy.egg-info/SOURCES.txt
brillixy.egg-info/dependency_links.txt
brillixy.egg-info/requires.txt
brillixy.egg-info/top_level.txt
brillixy/locale/ru/LC_MESSAGES/django.mo
brillixy/locale/ru/LC_MESSAGES/django.po
brillixy/static/.DS_Store
brillixy/static/brillixy/.DS_Store
brillixy/static/brillixy/bootstrap/.DS_Store
brillixy/static/brillixy/bootstrap/css/.DS_Store
brillixy/static/brillixy/bootstrap/css/bootstrap.min.css
brillixy/static/brillixy/bootstrap/js/.DS_Store
brillixy/static/brillixy/bootstrap/js/bootstrap.min.js
brillixy/static/brillixy/css/changeform.css
brillixy/static/brillixy/css/changelist.css
brillixy/static/brillixy/css/common.css
brillixy/static/brillixy/css/history.css
brillixy/static/brillixy/css/index.css
brillixy/static/brillixy/css/login.css
brillixy/static/brillixy/fontawesome/.DS_Store
brillixy/static/brillixy/fontawesome/css/font-awesome-ie7.min.css
brillixy/static/brillixy/fontawesome/css/font-awesome.css
brillixy/static/brillixy/fontawesome/css/font-awesome.min.css
brillixy/static/brillixy/fontawesome/font/FontAwesome.otf
brillixy/static/brillixy/fontawesome/font/fontawesome-webfont.eot
brillixy/static/brillixy/fontawesome/font/fontawesome-webfont.svg
brillixy/static/brillixy/fontawesome/font/fontawesome-webfont.ttf
brillixy/static/brillixy/fontawesome/font/fontawesome-webfont.woff
brillixy/static/brillixy/icons/icon-back.png
brillixy/static/brillixy/icons/icon-forward.png
brillixy/static/brillixy/jquery/jquery.min.js
brillixy/static/brillixy/js/changeform.js
brillixy/static/brillixy/js/changelist.js
brillixy/templates/admin/actions.html
brillixy/templates/admin/change_form.html
brillixy/templates/admin/change_list.html
brillixy/templates/admin/change_list_results.html
brillixy/templates/admin/date_hierarchy.html
brillixy/templates/admin/delete_confirmation.html
brillixy/templates/admin/delete_selected_confirmation.html
brillixy/templates/admin/filter.html
