Metadata-Version: 1.1
Name: brillixy
Version: 0.6.1
Summary: Customizations for Django admin interface.
Home-page: http://05bit.com/brillixy/
Author: Alexey Kinyov
Author-email: rudy@05bit.com
License: Creative Commons Attribution-NonCommercial 3.0 Unported License
Keywords: django,django-admin,utils,sugar
Platform: UNKNOWN
Classifier: Development Status :: 3 - Alpha
Classifier: Operating System :: OS Independent
Classifier: License :: Free for non-commercial use
Classifier: Intended Audience :: Developers
Classifier: Environment :: Web Environment
Classifier: Framework :: Django
Classifier: Intended Audience :: Developers
Classifier: Programming Language :: Python :: 2.5
Classifier: Programming Language :: Python :: 2.6
Classifier: Programming Language :: Python :: 2.7
